rkviewer/__init__.py
rkviewer/canvas/__init__.py
rkviewer/canvas/canvas.py
rkviewer/canvas/data.py
rkviewer/canvas/elements.py
rkviewer/canvas/geometry.py
rkviewer/canvas/overlays.py
rkviewer/canvas/state.py
rkviewer/canvas/utils.py
rkviewer/config.py
rkviewer/controller.py
rkviewer/events.py
rkviewer/forms.py
rkviewer/iodine.py
rkviewer/json/.default-settings.json
rkviewer/json/dark-settings.json
rkviewer/json/settings.json
rkviewer/main.py
rkviewer/mvc.py
rkviewer/plugin/__init__.py
rkviewer/plugin/api.py
rkviewer/plugin/canvas.py
rkviewer/plugin/classes.py
rkviewer/plugin/events.py
rkviewer/plugin_manage.py
rkviewer/resources/__init__.py
rkviewer/resources/AlignBottom_XP.png
rkviewer/resources/alignHorizCenter_XP.png
rkviewer/resources/alignHorizEqually_XP.png
rkviewer/resources/alignLeft_XP.png
rkviewer/resources/alignOnGrid_XP.png
rkviewer/resources/alignRight_XP.png
rkviewer/resources/alignTop_XP.png
rkviewer/resources/alignVertCenter_XP.png
rkviewer/resources/alignVertEqually_XP.png
rkviewer/resources/info-2-16.png
rkviewer/utils.py
rkviewer/view.py
rkviewer_plugins/addReaction.py
rkviewer_plugins/align_circle.py
rkviewer_plugins/arrow_designer.py
rkviewer_plugins/exportAntimony.py
rkviewer_plugins/exportSBML.py
rkviewer_plugins/importSBML.py
rkviewer_plugins/modelMetrics.py
rkviewer_plugins/networkX.py
rkviewer_plugins/randomNetwork.py
rkviewer_plugins/structuralAnalysis.py
sbcoyote-1.5.2.dist-info/entry_points.txt
sbcoyote-1.5.2.dist-info/LICENSE
sbcoyote-1.5.2.dist-info/METADATA
sbcoyote-1.5.2.dist-info/WHEEL
sbcoyote-1.5.2.dist-info/RECORD
